my_package/__init__.py
my_package/calculator.py
my_package/cli.py
my_package/new.py
pyproject_boilerplate-0.1.1.dist-info/METADATA
pyproject_boilerplate-0.1.1.dist-info/WHEEL
pyproject_boilerplate-0.1.1.dist-info/entry_points.txt
pyproject_boilerplate-0.1.1.dist-info/top_level.txt
pyproject_boilerplate-0.1.1.dist-info/RECORD
